apigateway_sdk_python/__init__.py
apigateway_sdk_python/signer.py
apigateway_sdk_python-1.0.0.dist-info/LICENSE
apigateway_sdk_python-1.0.0.dist-info/METADATA
apigateway_sdk_python-1.0.0.dist-info/WHEEL
apigateway_sdk_python-1.0.0.dist-info/top_level.txt
apigateway_sdk_python-1.0.0.dist-info/RECORD
