Metadata-Version: 2.1
Name: apigateway-sdk-python
Version: 1.0.0
Summary: apigateway-sdk-python for calling APIs Through App Authentication
Home-page: https://github.com/sber-platformv/apigateway-sdk-python.git
Author: SberTech
Author-email: platform_v_functions@sberbank.ru
Keywords: apigateway-sdk-python
Classifier: Development Status :: 3 - Alpha
Classifier: Intended Audience :: Developers
Classifier: License :: OSI Approved :: Apache Software License
Classifier: Programming Language :: Python :: 3
Classifier: Programming Language :: Python :: 3.8
Classifier: Programming Language :: Python :: 3.9
Classifier: Programming Language :: Python :: 3.10
Requires-Python: >=3.8
License-File: LICENSE
Requires-Dist: requests (>=2.6)
